LICENSE
MANIFEST.in
README.rst
setup.py
django_pluralize_pl.egg-info/PKG-INFO
django_pluralize_pl.egg-info/SOURCES.txt
django_pluralize_pl.egg-info/dependency_links.txt
django_pluralize_pl.egg-info/top_level.txt
pluralize_pl/__init__.py
pluralize_pl/templatetags/__init__.py
pluralize_pl/templatetags/pluralize_pl.py